Workbook

Sheet Sheet1
E1: Balance Sheet
E4: Particulars | F4: 2021 | G4: 2022 | H4: 2023 | I4: 2024 | J4: 2025
E5: Total Assets | F5: 15860 | G5: 20137 | H5: 25088 | I5: 32862 | J5: 41075
E6: Total Equity | F6: 7553 | G6: 9373 | H6: 11994 | I6: 14457 | J6: 16811
E7: Non-current Liabilities | F7: 1114 | G7: 1205 | H7: 1573 | I7: 5043 | J7: 2619
E8: current Liabilities | F8: 7193 | G8: 9559 | H8: 11521 | I8: 13362 | J8: 21645
E9: Inventories | F9: 7984 | G9: 12787 | H9: 14952 | I9: 16874 | J9: 24517
E10: Cash & Cash Equivalents | F10: 147 | G10: 117 | H10: 119 | I10: 272 | J10: 243
E11: Borrowings | F11: 0 | G11: 225 | H11: 1190 | I11: 3139 | J11: 420
E12: (IN CRORES)

Sheet Sheet2
C3: Statement of Profit & Loss
C6: Particulars | D6: 2021 | E6: 2022 | F6: 2023 | G6: 2024 | H6: 2025
C7: Revenue from operations | D7: 20602 | E7: 27210 | F7: 38270 | G7: 47114 | H7: 54842
C8: Total income | D8: 20783 | E8: 27456 | F8: 38569 | G8: 47624 | H8: 55335
C9: Employee Benefit Expense | D9: 911 | E9: 1143 | F9: 1362 | G9: 1503 | H9: 1717
C10: Finance Cost | D10: 181 | E10: 195 | F10: 240 | G10: 480 | H10: 767
C11: Depreciation | D11: 331 | E11: 347 | F11: 364 | G11: 447 | H11: 537
C12: Profit Before Tax | D12: 1233 | E12: 2932 | F12: 4465 | G12: 4607 | H12: 4481
C13: Net Profit | D13: 877 | E13: 2180 | F13: 3333 | G13: 3544 | H13: 3335
C14: EPS | D14: 9.88 | E14: 24.56 | F14: 37.54 | G14: 39.94 | H14: 37.6
C15: (IN CRORES)

Sheet Sheet3
C3: Cash Flow Sheet
C5: Particulars | D5: 2021 | E5: 2022 | F5: 2023 | G5: 2024 | H5: 2025
C6: Operating Cash Flow | D6: 4101 | E6: -1126 | F6: 1810 | G6: 2030 | H6: -170
C7: Investing Cash Flow | D7: -2744 | E7: 1564 | F7: -1653 | G7: -4634 | H7: 140
C8: Financing Cash Flow | D8: -1260 | E8: -468 | F8: -155 | G8: 2757 | H8: 1
C9: Net Increase in Cash | D9: 97 | E9: -30 | F9: 2 | G9: 153 | H9: -29
C10: (IN CRORES)

Sheet Sheet4
C3: Ratio Analysis
C6: Ratio | D6: 2021 | E6: 2022 | F6: 2023 | G6: 2024 | H6: 2025
C7: Current Ratio | D7: =Sheet1!F5/Sheet1!F8 -> 2.2049215 | E7: =Sheet1!G5/Sheet1!G8 -> 2.1066011 | F7: =Sheet1!H5/Sheet1!H8 -> 2.1775888 | G7: =Sheet1!I5/Sheet1!I8 -> 2.4593624 | H7: =Sheet1!J5/Sheet1!J8 -> 1.8976669
C8: Debt-to-Equity | D8: =Sheet1!F11/Sheet1!F6 -> 0 | E8: =Sheet1!G11/Sheet1!G6 -> 0.024005121 | F8: =Sheet1!H11/Sheet1!H6 -> 0.099216275 | G8: =Sheet1!I11/Sheet1!I6 -> 0.21712665 | H8: =Sheet1!J11/Sheet1!J6 -> 0.024983642
C9: Net Profit Margin | D9: =(Sheet2!D13/Sheet2!D7) -> 0.042568683 | E9: =(Sheet2!E13/Sheet2!E7) -> 0.080117604 | F9: =(Sheet2!F13/Sheet2!F7) -> 0.087091717 | G9: =(Sheet2!G13/Sheet2!G7) -> 0.075221802 | H9: =(Sheet2!H13/Sheet2!H7) -> 0.060811057
C10: ROE | D10: =(Sheet2!D13/Sheet1!F6) -> 0.1161128 | E10: =(Sheet2!E13/Sheet1!G6) -> 0.23258295 | F10: =(Sheet2!F13/Sheet1!H6) -> 0.27788894 | G10: =(Sheet2!G13/Sheet1!I6) -> 0.24514076 | H10: =(Sheet2!H13/Sheet1!J6) -> 0.19838201
C11: Asset Turnover | D11: =Sheet2!D7/Sheet1!F5 -> 1.2989912 | E11: =Sheet2!E7/Sheet1!G5 -> 1.351244 | F11: =Sheet2!F7/Sheet1!H5 -> 1.5254305 | G11: =Sheet2!G7/Sheet1!I5 -> 1.4336924 | H11: =Sheet2!H7/Sheet1!J5 -> 1.3351674

Sheet Charts
D7: Year | E7: Revenue from operations | P7: Year | Q7: ROE | AC7: Year | AD7: Net Profit Margin
D8: 2021 | E8: 20602 | P8: 2021 | Q8: 0.1161 | AC8: 2021 | AD8: =(Sheet4!D9) -> 0.042568683
D9: 2022 | E9: 27210 | P9: 2022 | Q9: 0.2326 | AC9: 2022 | AD9: =(Sheet4!E9) -> 0.080117604
D10: 2023 | E10: 38270 | P10: 2023 | Q10: 0.2779 | AC10: 2023 | AD10: =(Sheet4!F9) -> 0.087091717
D11: 2024 | E11: 47114 | P11: 2024 | Q11: 0.2451 | AC11: 2024 | AD11: =(Sheet4!G9) -> 0.075221802
D12: 2025 | E12: 54842 | P12: 2025 | Q12: 0.1984 | AC12: 2025 | AD12: =(Sheet4!H9) -> 0.060811057
D20: Year | E20: Net Profit
D21: 2021 | E21: 877 | Q21: Year | R21: Asset Turnover
D22: 2022 | E22: 2180 | Q22: 2021 | R22: 1.3
D23: 2023 | E23: 3333 | Q23: 2022 | R23: 1.35
D24: 2024 | E24: 3544 | Q24: 2023 | R24: 1.53
D25: 2025 | E25: 3335 | Q25: 2024 | R25: 1.43
Q26: 2025 | R26: 1.34
D35: Year | E35: Current Ratio
D36: 2021 | E36: 2.2
D37: 2022 | E37: 2.11
D38: 2023 | E38: 2.18
D39: 2024 | E39: 2.46
D40: 2025 | E40: 1.9

Sheet Dashboard
A1: TITAN COMPANY LTD. Financial Statement Analysis Dashboard (2021–2025)
